Metadata-Version: 1.0
Name: neuraldon
Version: 0.1.1
Summary: Python Package
Home-page: UNKNOWN
Author: UNKNOWN
Author-email: UNKNOWN
License: UNKNOWN
Platform: UNKNOWN
